LICENSE.txt
README.md
setup.py
ab_testing_module/__init__.py
ab_testing_module/abc_test.py
ab_testing_module/ad_modeling.py
ab_testing_module/df_viz.py
ab_testing_module.egg-info/PKG-INFO
ab_testing_module.egg-info/SOURCES.txt
ab_testing_module.egg-info/dependency_links.txt
ab_testing_module.egg-info/requires.txt
ab_testing_module.egg-info/top_level.txt