Metadata-Version: 2.1
Name: ab_testing_module
Version: 3.1.7
Summary: The AB Testing Module is a comprehensive suite designed for analyzing and reporting A/B test experiments, featuring functions for statistical analysis, advanced modeling, and data visualization to transform experimental results into actionable insights.
Home-page: https://github.com/knowusuboaky/ab_testing_module
Author: Kwadwo Daddy Nyame Owusu - Boakye
Author-email: kwadwo.owusuboakye@outlook.com
Keywords: statistics,data analysis,A/B testing,statistical modeling,data visualization,analysis toolbox,experimental analysis,hypothesis testing,effect size,power analysis,data science,machine learning,plotly visualizations,pandas data manipulation,numpy calculations,scipy statistics,statsmodels regression,matplotlib plotting,seaborn charts,data exploration,quantitative analysis,research tools,analytical reporting,decision support,inferential statistics,predictive modeling
Classifier: Development Status :: 3 - Alpha
Classifier: Intended Audience :: Developers
Classifier: Topic :: Software Development :: Build Tools
Classifier: License :: OSI Approved :: MIT License
Classifier: Programming Language :: Python :: 3
Classifier: Programming Language :: Python :: 3.6
Classifier: Programming Language :: Python :: 3.7
Classifier: Programming Language :: Python :: 3.8
Classifier: Programming Language :: Python :: 3.9
Classifier: Programming Language :: Python :: 3.10
Classifier: Programming Language :: Python :: 3.11
Classifier: Programming Language :: Python :: 3.12
Requires-Python: >=3.6
License-File: LICENSE.txt
Requires-Dist: numpy>=1.18.5
Requires-Dist: pandas>=1.0.5
Requires-Dist: scipy>=1.5.0
Requires-Dist: statsmodels>=0.11.1
Requires-Dist: matplotlib>=3.2.2
Requires-Dist: seaborn>=0.10.1
Requires-Dist: plotly>=4.8.2
Requires-Dist: scikit-learn>=0.23.1
Requires-Dist: jinja2>=2.11.2
